boibox.py
boibox-1.1.1.dist-info/LICENSE
boibox-1.1.1.dist-info/METADATA
boibox-1.1.1.dist-info/WHEEL
boibox-1.1.1.dist-info/entry_points.txt
boibox-1.1.1.dist-info/top_level.txt
boibox-1.1.1.dist-info/RECORD
