Metadata-Version: 2.1
Name: boibox
Version: 1.1.1
Summary: Python tool using asynchronous web requests to manage files on catbox.moe
Author: Astraea
License: zlib/libpng License
Project-URL: Homepage, https://github.com/Astraea0/boibox
Keywords: catbox,cli,asyncio
Classifier: Programming Language :: Python :: 3
Classifier: License :: OSI Approved :: zlib/libpng License
Classifier: Development Status :: 5 - Production/Stable
Classifier: Environment :: Console
Classifier: Framework :: AsyncIO
Classifier: Operating System :: OS Independent
Classifier: Topic :: Communications :: File Sharing
Classifier: Intended Audience :: End Users/Desktop
Classifier: Intended Audience :: Developers
Requires-Python: >=3.6
License-File: LICENSE
Requires-Dist: aiohttp (>=3.8.0)
Requires-Dist: tqdm (>=4.0)
